biapol_taurus/__init__.py
biapol_taurus/_project_file_transfer.py
biapol_taurus-0.1.1.dist-info/LICENSE
biapol_taurus-0.1.1.dist-info/METADATA
biapol_taurus-0.1.1.dist-info/WHEEL
biapol_taurus-0.1.1.dist-info/top_level.txt
biapol_taurus-0.1.1.dist-info/RECORD
