Metadata-Version: 2.1
Name: biapol-taurus
Version: 0.1.1
Summary: Bio-image analysis tools for the taurus cluster at TU Dresden
Home-page: https://github.com/haesleinhuepf/stackview/
Author: Robert Haase
Author-email: robert.haase@tu-dresden.de
License: UNKNOWN
Platform: UNKNOWN
Classifier: Programming Language :: Python :: 3
Classifier: License :: OSI Approved :: BSD License
Classifier: Operating System :: OS Independent
Classifier: Intended Audience :: Science/Research
Classifier: Development Status :: 3 - Alpha
Requires-Python: >=3.6
License-File: LICENSE
Requires-Dist: numpy (!=1.19.4)
Requires-Dist: stackview
